main.py
swisher_api_demo-0.1.0.dist-info/METADATA
swisher_api_demo-0.1.0.dist-info/WHEEL
swisher_api_demo-0.1.0.dist-info/entry_points.txt
swisher_api_demo-0.1.0.dist-info/top_level.txt
swisher_api_demo-0.1.0.dist-info/RECORD
