Metadata-Version: 2.1
Name: swisher-api-demo
Version: 0.1.0
Author-email: Michael Swisher <swishertmichael@gmail.com>
Project-URL: repository, https://github.com/mtswishr/api-demo
Requires-Python: >=3.10
Requires-Dist: requests >=2.31.0
Requires-Dist: click
Requires-Dist: python-dotenv
